PokebolaMari/__init__.py
PokebolaMari/pokemon.csv
PokebolaMari/random_pokemon.py
PokebolaMari-1.0.3.dist-info/METADATA
PokebolaMari-1.0.3.dist-info/WHEEL
PokebolaMari-1.0.3.dist-info/top_level.txt
PokebolaMari-1.0.3.dist-info/RECORD
