Metadata-Version: 2.1
Name: PokebolaMari
Version: 1.0.3
Summary: Esta libreria contiene la facilidad de generar un pokemon aleatorio como una pokebola
Author: Maria Cortes
Author-email: maris235@outlook.com
Requires-Dist: pandas
